odoo/addons/account_move_budget/README.rst
odoo/addons/account_move_budget/__init__.py
odoo/addons/account_move_budget/__manifest__.py
odoo/addons/account_move_budget/i18n/account_move_budget.pot
odoo/addons/account_move_budget/i18n/fr.po
odoo/addons/account_move_budget/i18n/it.po
odoo/addons/account_move_budget/models/__init__.py
odoo/addons/account_move_budget/models/account_move_budget.py
odoo/addons/account_move_budget/models/account_move_budget_line.py
odoo/addons/account_move_budget/readme/CONTRIBUTORS.rst
odoo/addons/account_move_budget/readme/DESCRIPTION.rst
odoo/addons/account_move_budget/readme/USAGE.rst
odoo/addons/account_move_budget/security/ir.model.access.csv
odoo/addons/account_move_budget/static/description/icon.png
odoo/addons/account_move_budget/static/description/index.html
odoo/addons/account_move_budget/views/account_move_budget_line_views.xml
odoo/addons/account_move_budget/views/account_move_budget_views.xml
odoo14_addon_account_move_budget-14.0.1.0.1.dist-info/METADATA
odoo14_addon_account_move_budget-14.0.1.0.1.dist-info/WHEEL
odoo14_addon_account_move_budget-14.0.1.0.1.dist-info/top_level.txt
odoo14_addon_account_move_budget-14.0.1.0.1.dist-info/RECORD
